tinyunicodeblock/__init__.py
tinyunicodeblock-1.3.dist-info/LICENSE
tinyunicodeblock-1.3.dist-info/METADATA
tinyunicodeblock-1.3.dist-info/WHEEL
tinyunicodeblock-1.3.dist-info/top_level.txt
tinyunicodeblock-1.3.dist-info/RECORD
