Metadata-Version: 2.1
Name: tinyunicodeblock
Version: 1.3
Summary: A tiny utility to get the Unicode block of a character
Author: WhoAteMyButter
License: MIT
Project-URL: Homepage, https://gitlab.com/whoatemybutter/tinyunicodeblock
Project-URL: Changelog, https://gitlab.com/whoatemybutter/tinyunicodeblock/-/blob/master/CHANGELOG.md
Project-URL: Issues, https://gitlab.com/whoatemybutter/tinyunicodeblock/-/issues
Keywords: unicode,unicode block,unicode character,block,character block,unicode utility
Classifier: Programming Language :: Python :: 3
Classifier: Programming Language :: Python :: 3 :: Only
Classifier: Programming Language :: Python :: 3.10
Classifier: Operating System :: OS Independent
Classifier: Topic :: Utilities
Classifier: Topic :: Other/Nonlisted Topic
Classifier: Development Status :: 3 - Alpha
Classifier: Intended Audience :: Other Audience
Classifier: Intended Audience :: Information Technology
Classifier: Intended Audience :: Developers
Classifier: License :: OSI Approved :: GNU General Public License v3 or later (GPLv3+)
Classifier: Natural Language :: English
Requires-Python: >=3.7
License-File: LICENSE
